pdf2emb_nlp/__init__.py
pdf2emb_nlp/arrange_text.py
pdf2emb_nlp/embedder.py
pdf2emb_nlp/json_creator.py
pdf2emb_nlp/logging.yaml
pdf2emb_nlp/process_user_queries.py
pdf2emb_nlp/scraper.py
pdf2emb_nlp/__pycache__/__init__.cpython-38.pyc
pdf2emb_nlp-0.2.0.dist-info/LICENSE
pdf2emb_nlp-0.2.0.dist-info/METADATA
pdf2emb_nlp-0.2.0.dist-info/WHEEL
pdf2emb_nlp-0.2.0.dist-info/top_level.txt
pdf2emb_nlp-0.2.0.dist-info/RECORD
